rest_swagger/__init__.py
rest_swagger/renderers.py
rest_swagger/settings.py
rest_swagger/views.py
rest_swagger/static/rest_swagger/app.bundle.css
rest_swagger/static/rest_swagger/app.bundle.js
rest_swagger/static/rest_swagger/favicon-16x16.png
rest_swagger/static/rest_swagger/favicon-32x32.png
rest_swagger/static/rest_swagger/logo.svg
rest_swagger/static/rest_swagger/logo_small.png
rest_swagger/static/rest_swagger/swagger.svg
rest_swagger/static/rest_swagger/vendors.bundle.css
rest_swagger/static/rest_swagger/vendors.bundle.js
rest_swagger/templates/rest_swagger/base.html
rest_swagger/templates/rest_swagger/index.html
rest_swagger/test/__init__.py
restswagger/__init__.py
test/__init__.py
rest_swagger-1.0.0.dist-info/LICENSE
rest_swagger-1.0.0.dist-info/METADATA
rest_swagger-1.0.0.dist-info/WHEEL
rest_swagger-1.0.0.dist-info/top_level.txt
rest_swagger-1.0.0.dist-info/RECORD
