Metadata-Version: 2.1
Name: rest-swagger
Version: 1.0.0
Summary: Implementation of Swagger UI for Django Rest Framework
Home-page: https://github.com/AjibsBaba/rest-swagger
Author: Samuel Ajibade
Author-email: samuelajibade22@gmail.com
License: LICENSE
Keywords: rest_swagger rest-swagger rest swagger djangorestframework documentation
Platform: UNKNOWN
Classifier: Intended Audience :: Developers
Classifier: License :: OSI Approved :: MIT License
Classifier: Development Status :: 5 - Production/Stable
Classifier: Operating System :: OS Independent
Classifier: Environment :: Web Environment
Classifier: Framework :: Django
Classifier: Framework :: Django :: 3.0
Classifier: Framework :: Django :: 2.0
Classifier: Framework :: Django :: 2.1
Classifier: Framework :: Django :: 2.2
Classifier: Topic :: Documentation
Classifier: Topic :: Software Development :: Code Generators
Classifier: Programming Language :: Python :: 3
Requires-Python: >=3.6
